{
  "$schema": "../icon.schema.json",
  "contributors": [
    "danielbayley"
  ],
  "tags": [
    "find",
    "search",
    "selection",
    "dashed"
  ],
  "categories": [
    "text",
    "cursors"
  ],
  "aliases": [
    {
      "name": "text-selection",
      "deprecationReason": "alias.name",
      "deprecated": true,
      "toBeRemovedInVersion": "v1.0"
    },
    {
      "name": "text-select",
      "deprecate": true,
      "deprecationReason": "alias.name",
      "toBeRemovedInVersion": "v1.0"
    }
  ]
}